CHANGES.txt
LICENSE.txt
MANIFEST.in
README.txt
TODO.txt
dwsettings-example.ini
setup.py
dwupload/__init__.py
dwupload/cli.py
dwupload/handlers.py
dwupload/webdav.py
dwupload.egg-info/PKG-INFO
dwupload.egg-info/SOURCES.txt
dwupload.egg-info/dependency_links.txt
dwupload.egg-info/entry_points.txt
dwupload.egg-info/not-zip-safe
dwupload.egg-info/requires.txt
dwupload.egg-info/top_level.txt