Metadata-Version: 1.1
Name: dwupload
Version: 0.1.3
Summary: Demandware upload file watcher. Keeps your files in sync with your sandbox so you don't have to use Eclipse
Home-page: UNKNOWN
Author: Charlie Choiniere
Author-email: nek4life@gmail.com
License: The MIT License (MIT)
